puretabix/__init__.py
puretabix/bgzip.py
puretabix/fsm.py
puretabix/mp.py
puretabix/py.typed
puretabix/tabix.py
puretabix/vcf.py
puretabix-5.4.0.dist-info/LICENSE.txt
puretabix-5.4.0.dist-info/METADATA
puretabix-5.4.0.dist-info/WHEEL
puretabix-5.4.0.dist-info/top_level.txt
puretabix-5.4.0.dist-info/RECORD
