Metadata-Version: 2.1
Name: puretabix
Version: 5.4.0
Summary: Pure python implementation Tabix reader.
Home-page: https://github.com/sanogenetics/puretabix
Author: Adam Faulconbridge
Author-email: afaulconbridge@googlemail.com
License: UNKNOWN
Platform: UNKNOWN
Provides-Extra: dev
Requires-Dist: pytest-cov ; extra == 'dev'
Requires-Dist: flake8 ; extra == 'dev'
Requires-Dist: black ; extra == 'dev'
Requires-Dist: mypy ; extra == 'dev'
Requires-Dist: pylint ; extra == 'dev'
Requires-Dist: pip-tools ; extra == 'dev'
Requires-Dist: pipdeptree ; extra == 'dev'
Requires-Dist: pre-commit ; extra == 'dev'
Requires-Dist: twine ; extra == 'dev'
Requires-Dist: scalene ; extra == 'dev'
